.gitignore
CHANGES.md
README.md
setup.py
pyramid_angularstarter/__init__.py
pyramid_angularstarter/scaffolds.py
pyramid_angularstarter.egg-info/PKG-INFO
pyramid_angularstarter.egg-info/SOURCES.txt
pyramid_angularstarter.egg-info/dependency_links.txt
pyramid_angularstarter.egg-info/entry_points.txt
pyramid_angularstarter.egg-info/not-zip-safe
pyramid_angularstarter.egg-info/requires.txt
pyramid_angularstarter.egg-info/top_level.txt
pyramid_angularstarter/angularstarter/CHANGES.md_tmpl
pyramid_angularstarter/angularstarter/README.md_tmpl
pyramid_angularstarter/angularstarter/development.ini_tmpl
pyramid_angularstarter/angularstarter/production.ini_tmpl
pyramid_angularstarter/angularstarter/setup.py_tmpl
pyramid_angularstarter/angularstarter/supervisord.conf_tmpl
pyramid_angularstarter/angularstarter/+package+/__init__.py
pyramid_angularstarter/angularstarter/+package+/views.py
pyramid_angularstarter/angularstarter/+package+/client-src/bower.json_tmpl
pyramid_angularstarter/angularstarter/+package+/client-src/gulpfile.js
pyramid_angularstarter/angularstarter/+package+/client-src/package.json
pyramid_angularstarter/angularstarter/+package+/client-src/scripts/app.coffee_tmpl
pyramid_angularstarter/angularstarter/+package+/client-src/views/app.html
pyramid_angularstarter/angularstarter/+package+/templates/home.html
pyramid_angularstarter/angularstarter/log/.keep
pyramid_angularstarter/angularstarter_w_user_model/.gitignore_tmpl
pyramid_angularstarter/angularstarter_w_user_model/CHANGES.md_tmpl
pyramid_angularstarter/angularstarter_w_user_model/README.md_tmpl
pyramid_angularstarter/angularstarter_w_user_model/alembic.ini_tmpl
pyramid_angularstarter/angularstarter_w_user_model/development.ini_tmpl
pyramid_angularstarter/angularstarter_w_user_model/setup.py_tmpl
pyramid_angularstarter/angularstarter_w_user_model/+package+/__init__.py_tmpl
pyramid_angularstarter/angularstarter_w_user_model/+package+/mailers.py
pyramid_angularstarter/angularstarter_w_user_model/+package+/models.py
pyramid_angularstarter/angularstarter_w_user_model/+package+/resource.py
pyramid_angularstarter/angularstarter_w_user_model/+package+/schemas.py
pyramid_angularstarter/angularstarter_w_user_model/+package+/security.py
pyramid_angularstarter/angularstarter_w_user_model/+package+/views.py
