Metadata-Version: 1.1
Name: pyramid-angularstarter
Version: 0.1
Summary: pyramid_angularstarter
Home-page: https://github.com/twillis/pyramid_angularstarter
Author: Tom Willis
Author-email: tom.willis@gmail.com
License: UNKNOWN
Keywords: web pyramid pylons
Platform: UNKNOWN
Classifier: Programming Language :: Python
Classifier: Framework :: Pyramid
Classifier: Topic :: Internet :: WWW/HTTP
Classifier: Topic :: Internet :: WWW/HTTP :: WSGI :: Application
